MANIFEST.in
README.rst
setup.py
student_ubl/__init__.py
student_ubl/auth.py
student_ubl/student.py
student_ubl/urls.py
student_ubl.egg-info/PKG-INFO
student_ubl.egg-info/SOURCES.txt
student_ubl.egg-info/dependency_links.txt
student_ubl.egg-info/not-zip-safe
student_ubl.egg-info/requires.txt
student_ubl.egg-info/top_level.txt