Metadata-Version: 1.1
Name: student-ubl
Version: 0.2
Summary: Simple API for accessing data student budiluhur site
Home-page: https://github.com/yanwarsolah/student-ubl
Author: Yanwar Solahudin
Author-email: yanwarsolah@gmail.com
License: MIT
Platform: UNKNOWN
Classifier: Development Status :: 4 - Beta
Classifier: License :: OSI Approved :: MIT License
Classifier: Programming Language :: Python :: 2
Classifier: Programming Language :: Python :: 2.7
Classifier: Programming Language :: Python :: 3
Classifier: Programming Language :: Python :: 3.3
Classifier: Programming Language :: Python :: 3.4
